flashfocus/__init__.py
flashfocus/cli.py
flashfocus/client.py
flashfocus/compat.py
flashfocus/config.py
flashfocus/default_config.yml
flashfocus/display.py
flashfocus/errors.py
flashfocus/flasher.py
flashfocus/logging.py
flashfocus/pid.py
flashfocus/producer.py
flashfocus/router.py
flashfocus/server.py
flashfocus/sockets.py
flashfocus/types.py
flashfocus/util.py
flashfocus/display_protocols/__init__.py
flashfocus/display_protocols/sway.py
flashfocus/display_protocols/x11.py
flashfocus-2.4.1.data/scripts/nc_flash_window
flashfocus-2.4.1.dist-info/LICENSE
flashfocus-2.4.1.dist-info/METADATA
flashfocus-2.4.1.dist-info/WHEEL
flashfocus-2.4.1.dist-info/entry_points.txt
flashfocus-2.4.1.dist-info/top_level.txt
flashfocus-2.4.1.dist-info/RECORD
