Metadata-Version: 2.1
Name: flashfocus
Version: 2.4.1
Summary: Simple focus animations for tiling window managers.
Author-email: Fenner Macrae <fmacrae.dev@gmail.com>
License: Copyright (c) 2018 Fenner Macrae
Keywords: xorg,x11,flash,focus,i3,sway,wlroots,bspwm,awesomewm,herbsluftwm
Classifier: License :: OSI Approved :: MIT License
Classifier: Operating System :: POSIX :: Linux
Classifier: Development Status :: 6 - Mature
Classifier: Programming Language :: Python :: 3 :: Only
Classifier: Programming Language :: Python :: 3.8
Classifier: Programming Language :: Python :: 3.9
Classifier: Programming Language :: Python :: 3.10
Classifier: Programming Language :: Python :: 3.11
Classifier: Programming Language :: Python :: 3.12
Classifier: Topic :: Desktop Environment :: Window Managers
Classifier: Topic :: Desktop Environment
Requires-Python: >=3.8
License-File: LICENSE
Requires-Dist: xcffib <1.0,>=0.6.0
Requires-Dist: click <9.0,>=6.7
Requires-Dist: cffi <2.0,>=1.11
Requires-Dist: xpybutil <1.0,>=0.0.6
Requires-Dist: marshmallow <4.0,>=2.15
Requires-Dist: pyyaml >=5.1
Requires-Dist: i3ipc <3.0,>=2.1.1
Provides-Extra: dev
Requires-Dist: bump2version <2.0,>=1.0 ; extra == 'dev'
Requires-Dist: factory-boy <4.0,>=3.0 ; extra == 'dev'
Requires-Dist: pre-commit <4.0,>=3.4 ; extra == 'dev'
Requires-Dist: pytest <8.0,>=7.4 ; extra == 'dev'
Requires-Dist: pytest-cov <5.0,>=4.1 ; extra == 'dev'
Requires-Dist: pytest-factoryboy <3.0,>=2.1 ; extra == 'dev'
Requires-Dist: pytest-lazy-fixture <1.0,>=0.6 ; extra == 'dev'
Requires-Dist: pytest-mock <4.0,>=3.7 ; extra == 'dev'
Requires-Dist: types-factory-boy ; extra == 'dev'
Requires-Dist: types-pytest-lazy-fixture ; extra == 'dev'
Requires-Dist: types-pyyaml ; extra == 'dev'
